pyfuncdb/__init__.py
pyfuncdb/registra.py
pyfuncdb/ricorda.py
pyfuncdb/serie_temporale.py
pyfuncdb-0.0.1.dist-info/LICENSE
pyfuncdb-0.0.1.dist-info/METADATA
pyfuncdb-0.0.1.dist-info/WHEEL
pyfuncdb-0.0.1.dist-info/top_level.txt
pyfuncdb-0.0.1.dist-info/RECORD
